limpyd_extensions/__init__.py
limpyd_extensions/related.py
limpyd_extensions/dynamic/__init__.py
limpyd_extensions/dynamic/collection.py
limpyd_extensions/dynamic/fields.py
limpyd_extensions/dynamic/model.py
limpyd_extensions/dynamic/related.py
redis_limpyd_extensions-2.1.dist-info/LICENSE
redis_limpyd_extensions-2.1.dist-info/METADATA
redis_limpyd_extensions-2.1.dist-info/WHEEL
redis_limpyd_extensions-2.1.dist-info/top_level.txt
redis_limpyd_extensions-2.1.dist-info/zip-safe
redis_limpyd_extensions-2.1.dist-info/RECORD
